<FontData>
  <Texture>
    data/fonts/font_pixel_noshadow.png
  </Texture>
  <LineHeight>
    7
  </LineHeight>
  <CharSpace>
    0
  </CharSpace>
  <WordSpace>
    6
  </WordSpace>
  <QuadChar id="32" offset_x="0" offset_y="0" rect_h="11" rect_w="3" rect_x="0" rect_y="0" width="3" >
  </QuadChar>
  <QuadChar id="33" offset_x="0" offset_y="0" rect_h="11" rect_w="2" rect_x="4" rect_y="0" width="2" >
  </QuadChar>
  <QuadChar id="34" offset_x="0" offset_y="0" rect_h="11" rect_w="4" rect_x="7" rect_y="0" width="4" >
  </QuadChar>
  <QuadChar id="35" offset_x="0" offset_y="0" rect_h="11" rect_w="6" rect_x="12" rect_y="0" width="6" >
  </QuadChar>
  <QuadChar id="36" offset_x="0" offset_y="0" rect_h="11" rect_w="6" rect_x="19" rect_y="0" width="6" >
  </QuadChar>
  <QuadChar id="37" offset_x="0" offset_y="0" rect_h="11" rect_w="6" rect_x="26" rect_y="0" width="6" >
  </QuadChar>
  <QuadChar id="38" offset_x="0" offset_y="0" rect_h="11" rect_w="6" rect_x="33" rect_y="0" width="6" >
  </QuadChar>
  <QuadChar id="39" offset_x="0" offset_y="0" rect_h="11" rect_w="2" rect_x="40" rect_y="0" width="2" >
  </QuadChar>
  <QuadChar id="40" offset_x="0" offset_y="0" rect_h="11" rect_w="6" rect_x="43" rect_y="0" width="6" >
  </QuadChar>
  <QuadChar id="41" offset_x="0" offset_y="0" rect_h="11" rect_w="6" rect_x="50" rect_y="0" width="6" >
  </QuadChar>
  <QuadChar id="42" offset_x="0" offset_y="0" rect_h="11" rect_w="6" rect_x="57" rect_y="0" width="6" >
  </QuadChar>
  <QuadChar id="43" offset_x="0" offset_y="0" rect_h="11" rect_w="6" rect_x="64" rect_y="0" width="6" >
  </QuadChar>
  <QuadChar id="44" offset_x="0" offset_y="0" rect_h="11" rect_w="3" rect_x="71" rect_y="0" width="3" >
  </QuadChar>
  <QuadChar id="45" offset_x="0" offset_y="0" rect_h="11" rect_w="6" rect_x="75" rect_y="0" width="6" >
  </QuadChar>
  <QuadChar id="46" offset_x="0" offset_y="0" rect_h="11" rect_w="2" rect_x="82" rect_y="0" width="2" >
  </QuadChar>
  <QuadChar id="47" offset_x="0" offset_y="0" rect_h="11" rect_w="6" rect_x="85" rect_y="0" width="6" >
  </QuadChar>
  <QuadChar id="48" offset_x="0" offset_y="0" rect_h="11" rect_w="6" rect_x="92" rect_y="0" width="6" >
  </QuadChar>
  <QuadChar id="49" offset_x="0" offset_y="0" rect_h="11" rect_w="4" rect_x="99" rect_y="0" width="4" >
  </QuadChar>
  <QuadChar id="50" offset_x="0" offset_y="0" rect_h="11" rect_w="6" rect_x="104" rect_y="0" width="6" >
  </QuadChar>
  <QuadChar id="51" offset_x="0" offset_y="0" rect_h="11" rect_w="6" rect_x="111" rect_y="0" width="6" >
  </QuadChar>
  <QuadChar id="52" offset_x="0" offset_y="0" rect_h="11" rect_w="6" rect_x="118" rect_y="0" width="6" >
  </QuadChar>
  <QuadChar id="53" offset_x="0" offset_y="0" rect_h="11" rect_w="6" rect_x="125" rect_y="0" width="6" >
  </QuadChar>
  <QuadChar id="54" offset_x="0" offset_y="0" rect_h="11" rect_w="6" rect_x="132" rect_y="0" width="6" >
  </QuadChar>
  <QuadChar id="55" offset_x="0" offset_y="0" rect_h="11" rect_w="6" rect_x="139" rect_y="0" width="6" >
  </QuadChar>
  <QuadChar id="56" offset_x="0" offset_y="0" rect_h="11" rect_w="6" rect_x="146" rect_y="0" width="6" >
  </QuadChar>
  <QuadChar id="57" offset_x="0" offset_y="0" rect_h="11" rect_w="6" rect_x="153" rect_y="0" width="6" >
  </QuadChar>
  <QuadChar id="58" offset_x="0" offset_y="0" rect_h="11" rect_w="2" rect_x="160" rect_y="0" width="2" >
  </QuadChar>
  <QuadChar id="59" offset_x="0" offset_y="0" rect_h="11" rect_w="2" rect_x="163" rect_y="0" width="2" >
  </QuadChar>
  <QuadChar id="60" offset_x="0" offset_y="0" rect_h="11" rect_w="6" rect_x="166" rect_y="0" width="6" >
  </QuadChar>
  <QuadChar id="61" offset_x="0" offset_y="0" rect_h="11" rect_w="6" rect_x="173" rect_y="0" width="6" >
  </QuadChar>
  <QuadChar id="62" offset_x="0" offset_y="0" rect_h="11" rect_w="6" rect_x="180" rect_y="0" width="6" >
  </QuadChar>
  <QuadChar id="63" offset_x="0" offset_y="0" rect_h="11" rect_w="6" rect_x="187" rect_y="0" width="6" >
  </QuadChar>
  <QuadChar id="64" offset_x="0" offset_y="0" rect_h="11" rect_w="6" rect_x="194" rect_y="0" width="6" >
  </QuadChar>
  <QuadChar id="65" offset_x="0" offset_y="0" rect_h="11" rect_w="6" rect_x="201" rect_y="0" width="6" >
  </QuadChar>
  <QuadChar id="66" offset_x="0" offset_y="0" rect_h="11" rect_w="6" rect_x="208" rect_y="0" width="6" >
  </QuadChar>
  <QuadChar id="67" offset_x="0" offset_y="0" rect_h="11" rect_w="6" rect_x="215" rect_y="0" width="6" >
  </QuadChar>
  <QuadChar id="68" offset_x="0" offset_y="0" rect_h="11" rect_w="6" rect_x="222" rect_y="0" width="6" >
  </QuadChar>
  <QuadChar id="69" offset_x="0" offset_y="0" rect_h="11" rect_w="6" rect_x="229" rect_y="0" width="6" >
  </QuadChar>
  <QuadChar id="70" offset_x="0" offset_y="0" rect_h="11" rect_w="6" rect_x="236" rect_y="0" width="6" >
  </QuadChar>
  <QuadChar id="71" offset_x="0" offset_y="0" rect_h="11" rect_w="6" rect_x="243" rect_y="0" width="6" >
  </QuadChar>
  <QuadChar id="72" offset_x="0" offset_y="0" rect_h="11" rect_w="6" rect_x="250" rect_y="0" width="6" >
  </QuadChar>
  <QuadChar id="73" offset_x="0" offset_y="0" rect_h="11" rect_w="5" rect_x="257" rect_y="0" width="5" >
  </QuadChar>
  <QuadChar id="74" offset_x="0" offset_y="0" rect_h="11" rect_w="6" rect_x="263" rect_y="0" width="6" >
  </QuadChar>
  <QuadChar id="75" offset_x="0" offset_y="0" rect_h="11" rect_w="6" rect_x="270" rect_y="0" width="6" >
  </QuadChar>
  <QuadChar id="76" offset_x="0" offset_y="0" rect_h="11" rect_w="5" rect_x="277" rect_y="0" width="5" >
  </QuadChar>
  <QuadChar id="77" offset_x="0" offset_y="0" rect_h="11" rect_w="6" rect_x="283" rect_y="0" width="6" >
  </QuadChar>
  <QuadChar id="78" offset_x="0" offset_y="0" rect_h="11" rect_w="6" rect_x="290" rect_y="0" width="6" >
  </QuadChar>
  <QuadChar id="79" offset_x="0" offset_y="0" rect_h="11" rect_w="6" rect_x="297" rect_y="0" width="6" >
  </QuadChar>
  <QuadChar id="80" offset_x="0" offset_y="0" rect_h="11" rect_w="5" rect_x="304" rect_y="0" width="5" >
  </QuadChar>
  <QuadChar id="81" offset_x="0" offset_y="0" rect_h="11" rect_w="6" rect_x="310" rect_y="0" width="6" >
  </QuadChar>
  <QuadChar id="82" offset_x="0" offset_y="0" rect_h="11" rect_w="6" rect_x="317" rect_y="0" width="6" >
  </QuadChar>
  <QuadChar id="83" offset_x="0" offset_y="0" rect_h="11" rect_w="6" rect_x="324" rect_y="0" width="6" >
  </QuadChar>
  <QuadChar id="84" offset_x="0" offset_y="0" rect_h="11" rect_w="6" rect_x="331" rect_y="0" width="6" >
  </QuadChar>
  <QuadChar id="85" offset_x="0" offset_y="0" rect_h="11" rect_w="6" rect_x="338" rect_y="0" width="6" >
  </QuadChar>
  <QuadChar id="86" offset_x="0" offset_y="0" rect_h="11" rect_w="6" rect_x="345" rect_y="0" width="6" >
  </QuadChar>
  <QuadChar id="87" offset_x="0" offset_y="0" rect_h="11" rect_w="6" rect_x="352" rect_y="0" width="6" >
  </QuadChar>
  <QuadChar id="88" offset_x="0" offset_y="0" rect_h="11" rect_w="6" rect_x="359" rect_y="0" width="6" >
  </QuadChar>
  <QuadChar id="89" offset_x="0" offset_y="0" rect_h="11" rect_w="6" rect_x="366" rect_y="0" width="6" >
  </QuadChar>
  <QuadChar id="90" offset_x="0" offset_y="0" rect_h="11" rect_w="6" rect_x="373" rect_y="0" width="6" >
  </QuadChar>
  <QuadChar id="91" offset_x="0" offset_y="0" rect_h="11" rect_w="6" rect_x="380" rect_y="0" width="6" >
  </QuadChar>
  <QuadChar id="92" offset_x="0" offset_y="0" rect_h="11" rect_w="6" rect_x="387" rect_y="0" width="6" >
  </QuadChar>
  <QuadChar id="93" offset_x="0" offset_y="0" rect_h="11" rect_w="6" rect_x="394" rect_y="0" width="6" >
  </QuadChar>
  <QuadChar id="94" offset_x="0" offset_y="0" rect_h="11" rect_w="6" rect_x="401" rect_y="0" width="6" >
  </QuadChar>
  <QuadChar id="95" offset_x="0" offset_y="0" rect_h="11" rect_w="6" rect_x="408" rect_y="0" width="6" >
  </QuadChar>
  <QuadChar id="96" offset_x="0" offset_y="0" rect_h="11" rect_w="3" rect_x="415" rect_y="0" width="3" >
  </QuadChar>
  <QuadChar id="97" offset_x="0" offset_y="0" rect_h="11" rect_w="4" rect_x="419" rect_y="0" width="4" >
  </QuadChar>
  <QuadChar id="98" offset_x="0" offset_y="0" rect_h="11" rect_w="4" rect_x="424" rect_y="0" width="4" >
  </QuadChar>
  <QuadChar id="99" offset_x="0" offset_y="0" rect_h="11" rect_w="4" rect_x="429" rect_y="0" width="4" >
  </QuadChar>
  <QuadChar id="100" offset_x="0" offset_y="0" rect_h="11" rect_w="4" rect_x="434" rect_y="0" width="4" >
  </QuadChar>
  <QuadChar id="101" offset_x="0" offset_y="0" rect_h="11" rect_w="4" rect_x="439" rect_y="0" width="4" >
  </QuadChar>
  <QuadChar id="102" offset_x="0" offset_y="0" rect_h="11" rect_w="4" rect_x="444" rect_y="0" width="4" >
  </QuadChar>
  <QuadChar id="103" offset_x="0" offset_y="0" rect_h="11" rect_w="4" rect_x="449" rect_y="0" width="4" >
  </QuadChar>
  <QuadChar id="104" offset_x="0" offset_y="0" rect_h="11" rect_w="4" rect_x="454" rect_y="0" width="4" >
  </QuadChar>
  <QuadChar id="105" offset_x="0" offset_y="0" rect_h="11" rect_w="2" rect_x="459" rect_y="0" width="2" >
  </QuadChar>
  <QuadChar id="106" offset_x="0" offset_y="0" rect_h="11" rect_w="4" rect_x="462" rect_y="0" width="4" >
  </QuadChar>
  <QuadChar id="107" offset_x="0" offset_y="0" rect_h="11" rect_w="4" rect_x="467" rect_y="0" width="4" >
  </QuadChar>
  <QuadChar id="108" offset_x="0" offset_y="0" rect_h="11" rect_w="2" rect_x="472" rect_y="0" width="2" >
  </QuadChar>
  <QuadChar id="109" offset_x="0" offset_y="0" rect_h="11" rect_w="6" rect_x="475" rect_y="0" width="6" >
  </QuadChar>
  <QuadChar id="110" offset_x="0" offset_y="0" rect_h="11" rect_w="4" rect_x="482" rect_y="0" width="4" >
  </QuadChar>
  <QuadChar id="111" offset_x="0" offset_y="0" rect_h="11" rect_w="4" rect_x="487" rect_y="0" width="4" >
  </QuadChar>
  <QuadChar id="112" offset_x="0" offset_y="0" rect_h="11" rect_w="4" rect_x="492" rect_y="0" width="4" >
  </QuadChar>
  <QuadChar id="113" offset_x="0" offset_y="0" rect_h="11" rect_w="4" rect_x="497" rect_y="0" width="4" >
  </QuadChar>
  <QuadChar id="114" offset_x="0" offset_y="0" rect_h="11" rect_w="4" rect_x="502" rect_y="0" width="4" >
  </QuadChar>
  <QuadChar id="115" offset_x="0" offset_y="0" rect_h="11" rect_w="4" rect_x="507" rect_y="0" width="4" >
  </QuadChar>
  <QuadChar id="116" offset_x="0" offset_y="0" rect_h="11" rect_w="4" rect_x="512" rect_y="0" width="4" >
  </QuadChar>
  <QuadChar id="117" offset_x="0" offset_y="0" rect_h="11" rect_w="4" rect_x="517" rect_y="0" width="4" >
  </QuadChar>
  <QuadChar id="118" offset_x="0" offset_y="0" rect_h="11" rect_w="4" rect_x="522" rect_y="0" width="4" >
  </QuadChar>
  <QuadChar id="119" offset_x="0" offset_y="0" rect_h="11" rect_w="6" rect_x="527" rect_y="0" width="6" >
  </QuadChar>
  <QuadChar id="120" offset_x="0" offset_y="0" rect_h="11" rect_w="4" rect_x="534" rect_y="0" width="4" >
  </QuadChar>
  <QuadChar id="121" offset_x="0" offset_y="0" rect_h="11" rect_w="4" rect_x="539" rect_y="0" width="4" >
  </QuadChar>
  <QuadChar id="122" offset_x="0" offset_y="0" rect_h="11" rect_w="4" rect_x="544" rect_y="0" width="4" >
  </QuadChar>
  <QuadChar id="124" offset_x="0" offset_y="0" rect_h="11" rect_w="6" rect_x="549" rect_y="0" width="6" >
  </QuadChar>
  <QuadChar id="126" offset_x="0" offset_y="0" rect_h="11" rect_w="6" rect_x="556" rect_y="0" width="6" >
  </QuadChar>
  <QuadChar id="161" offset_x="0" offset_y="0" rect_h="11" rect_w="3" rect_x="563" rect_y="0" width="3" >
  </QuadChar>
  <QuadChar id="169" offset_x="0" offset_y="0" rect_h="11" rect_w="7" rect_x="567" rect_y="0" width="7" >
  </QuadChar>
  <QuadChar id="171" offset_x="0" offset_y="0" rect_h="11" rect_w="6" rect_x="575" rect_y="0" width="6" >
  </QuadChar>
  <QuadChar id="172" offset_x="0" offset_y="0" rect_h="11" rect_w="6" rect_x="582" rect_y="0" width="6" >
  </QuadChar>
  <QuadChar id="187" offset_x="0" offset_y="0" rect_h="11" rect_w="6" rect_x="589" rect_y="0" width="6" >
  </QuadChar>
  <QuadChar id="191" offset_x="0" offset_y="0" rect_h="11" rect_w="5" rect_x="596" rect_y="0" width="5" >
  </QuadChar>
  <QuadChar id="192" offset_x="0" offset_y="0" rect_h="11" rect_w="6" rect_x="602" rect_y="0" width="6" >
  </QuadChar>
  <QuadChar id="193" offset_x="0" offset_y="0" rect_h="11" rect_w="6" rect_x="609" rect_y="0" width="6" >
  </QuadChar>
  <QuadChar id="194" offset_x="0" offset_y="0" rect_h="11" rect_w="6" rect_x="616" rect_y="0" width="6" >
  </QuadChar>
  <QuadChar id="195" offset_x="0" offset_y="0" rect_h="11" rect_w="6" rect_x="623" rect_y="0" width="6" >
  </QuadChar>
  <QuadChar id="196" offset_x="0" offset_y="0" rect_h="11" rect_w="6" rect_x="630" rect_y="0" width="6" >
  </QuadChar>
  <QuadChar id="197" offset_x="0" offset_y="0" rect_h="11" rect_w="6" rect_x="637" rect_y="0" width="6" >
  </QuadChar>
  <QuadChar id="199" offset_x="0" offset_y="0" rect_h="11" rect_w="6" rect_x="644" rect_y="0" width="6" >
  </QuadChar>
  <QuadChar id="200" offset_x="0" offset_y="0" rect_h="11" rect_w="6" rect_x="651" rect_y="0" width="6" >
  </QuadChar>
  <QuadChar id="201" offset_x="0" offset_y="0" rect_h="11" rect_w="6" rect_x="658" rect_y="0" width="6" >
  </QuadChar>
  <QuadChar id="202" offset_x="0" offset_y="0" rect_h="11" rect_w="6" rect_x="665" rect_y="0" width="6" >
  </QuadChar>
  <QuadChar id="203" offset_x="0" offset_y="0" rect_h="11" rect_w="6" rect_x="672" rect_y="0" width="6" >
  </QuadChar>
  <QuadChar id="204" offset_x="0" offset_y="0" rect_h="11" rect_w="3" rect_x="679" rect_y="0" width="3" >
  </QuadChar>
  <QuadChar id="205" offset_x="0" offset_y="0" rect_h="11" rect_w="5" rect_x="683" rect_y="0" width="5" >
  </QuadChar>
  <QuadChar id="206" offset_x="0" offset_y="0" rect_h="11" rect_w="5" rect_x="689" rect_y="0" width="5" >
  </QuadChar>
  <QuadChar id="207" offset_x="0" offset_y="0" rect_h="11" rect_w="5" rect_x="695" rect_y="0" width="5" >
  </QuadChar>
  <QuadChar id="209" offset_x="0" offset_y="0" rect_h="11" rect_w="6" rect_x="701" rect_y="0" width="6" >
  </QuadChar>
  <QuadChar id="211" offset_x="0" offset_y="0" rect_h="11" rect_w="6" rect_x="708" rect_y="0" width="6" >
  </QuadChar>
  <QuadChar id="212" offset_x="0" offset_y="0" rect_h="11" rect_w="6" rect_x="715" rect_y="0" width="6" >
  </QuadChar>
  <QuadChar id="213" offset_x="0" offset_y="0" rect_h="11" rect_w="6" rect_x="722" rect_y="0" width="6" >
  </QuadChar>
  <QuadChar id="214" offset_x="0" offset_y="0" rect_h="11" rect_w="6" rect_x="729" rect_y="0" width="6" >
  </QuadChar>
  <QuadChar id="216" offset_x="0" offset_y="0" rect_h="11" rect_w="6" rect_x="736" rect_y="0" width="6" >
  </QuadChar>
  <QuadChar id="217" offset_x="0" offset_y="0" rect_h="11" rect_w="6" rect_x="743" rect_y="0" width="6" >
  </QuadChar>
  <QuadChar id="218" offset_x="0" offset_y="0" rect_h="11" rect_w="6" rect_x="750" rect_y="0" width="6" >
  </QuadChar>
  <QuadChar id="219" offset_x="0" offset_y="0" rect_h="11" rect_w="6" rect_x="757" rect_y="0" width="6" >
  </QuadChar>
  <QuadChar id="220" offset_x="0" offset_y="0" rect_h="11" rect_w="6" rect_x="764" rect_y="0" width="6" >
  </QuadChar>
  <QuadChar id="223" offset_x="0" offset_y="0" rect_h="11" rect_w="6" rect_x="771" rect_y="0" width="6" >
  </QuadChar>
  <QuadChar id="224" offset_x="0" offset_y="0" rect_h="11" rect_w="4" rect_x="778" rect_y="0" width="4" >
  </QuadChar>
  <QuadChar id="225" offset_x="0" offset_y="0" rect_h="11" rect_w="4" rect_x="783" rect_y="0" width="4" >
  </QuadChar>
  <QuadChar id="226" offset_x="0" offset_y="0" rect_h="11" rect_w="4" rect_x="788" rect_y="0" width="4" >
  </QuadChar>
  <QuadChar id="227" offset_x="0" offset_y="0" rect_h="11" rect_w="4" rect_x="793" rect_y="0" width="4" >
  </QuadChar>
  <QuadChar id="228" offset_x="0" offset_y="0" rect_h="11" rect_w="4" rect_x="798" rect_y="0" width="4" >
  </QuadChar>
  <QuadChar id="229" offset_x="0" offset_y="0" rect_h="11" rect_w="4" rect_x="803" rect_y="0" width="4" >
  </QuadChar>
  <QuadChar id="231" offset_x="0" offset_y="0" rect_h="11" rect_w="4" rect_x="808" rect_y="0" width="4" >
  </QuadChar>
  <QuadChar id="232" offset_x="0" offset_y="0" rect_h="11" rect_w="4" rect_x="813" rect_y="0" width="4" >
  </QuadChar>
  <QuadChar id="233" offset_x="0" offset_y="0" rect_h="11" rect_w="4" rect_x="818" rect_y="0" width="4" >
  </QuadChar>
  <QuadChar id="234" offset_x="0" offset_y="0" rect_h="11" rect_w="4" rect_x="823" rect_y="0" width="4" >
  </QuadChar>
  <QuadChar id="235" offset_x="0" offset_y="0" rect_h="11" rect_w="4" rect_x="828" rect_y="0" width="4" >
  </QuadChar>
  <QuadChar id="236" offset_x="0" offset_y="0" rect_h="11" rect_w="3" rect_x="833" rect_y="0" width="3" >
  </QuadChar>
  <QuadChar id="237" offset_x="0" offset_y="0" rect_h="11" rect_w="3" rect_x="837" rect_y="0" width="3" >
  </QuadChar>
  <QuadChar id="238" offset_x="0" offset_y="0" rect_h="11" rect_w="4" rect_x="841" rect_y="0" width="4" >
  </QuadChar>
  <QuadChar id="239" offset_x="0" offset_y="0" rect_h="11" rect_w="4" rect_x="846" rect_y="0" width="4" >
  </QuadChar>
  <QuadChar id="241" offset_x="0" offset_y="0" rect_h="11" rect_w="5" rect_x="851" rect_y="0" width="5" >
  </QuadChar>
  <QuadChar id="243" offset_x="0" offset_y="0" rect_h="11" rect_w="4" rect_x="857" rect_y="0" width="4" >
  </QuadChar>
  <QuadChar id="244" offset_x="0" offset_y="0" rect_h="11" rect_w="4" rect_x="862" rect_y="0" width="4" >
  </QuadChar>
  <QuadChar id="245" offset_x="0" offset_y="0" rect_h="11" rect_w="4" rect_x="867" rect_y="0" width="4" >
  </QuadChar>
  <QuadChar id="246" offset_x="0" offset_y="0" rect_h="11" rect_w="4" rect_x="872" rect_y="0" width="4" >
  </QuadChar>
  <QuadChar id="248" offset_x="0" offset_y="0" rect_h="11" rect_w="6" rect_x="877" rect_y="0" width="6" >
  </QuadChar>
  <QuadChar id="249" offset_x="0" offset_y="0" rect_h="11" rect_w="4" rect_x="884" rect_y="0" width="4" >
  </QuadChar>
  <QuadChar id="250" offset_x="0" offset_y="0" rect_h="11" rect_w="4" rect_x="889" rect_y="0" width="4" >
  </QuadChar>
  <QuadChar id="251" offset_x="0" offset_y="0" rect_h="11" rect_w="4" rect_x="894" rect_y="0" width="4" >
  </QuadChar>
  <QuadChar id="252" offset_x="0" offset_y="0" rect_h="11" rect_w="4" rect_x="899" rect_y="0" width="4" >
  </QuadChar>
  <QuadChar id="260" offset_x="0" offset_y="0" rect_h="11" rect_w="6" rect_x="904" rect_y="0" width="6" >
  </QuadChar>
  <QuadChar id="261" offset_x="0" offset_y="0" rect_h="11" rect_w="5" rect_x="911" rect_y="0" width="5" >
  </QuadChar>
  <QuadChar id="262" offset_x="0" offset_y="0" rect_h="11" rect_w="6" rect_x="917" rect_y="0" width="6" >
  </QuadChar>
  <QuadChar id="263" offset_x="0" offset_y="0" rect_h="11" rect_w="4" rect_x="924" rect_y="0" width="4" >
  </QuadChar>
  <QuadChar id="280" offset_x="0" offset_y="0" rect_h="11" rect_w="5" rect_x="929" rect_y="0" width="5" >
  </QuadChar>
  <QuadChar id="281" offset_x="0" offset_y="0" rect_h="11" rect_w="4" rect_x="935" rect_y="0" width="4" >
  </QuadChar>
  <QuadChar id="321" offset_x="0" offset_y="0" rect_h="11" rect_w="6" rect_x="940" rect_y="0" width="6" >
  </QuadChar>
  <QuadChar id="322" offset_x="0" offset_y="0" rect_h="11" rect_w="4" rect_x="947" rect_y="0" width="4" >
  </QuadChar>
  <QuadChar id="323" offset_x="0" offset_y="0" rect_h="11" rect_w="6" rect_x="952" rect_y="0" width="6" >
  </QuadChar>
  <QuadChar id="324" offset_x="0" offset_y="0" rect_h="11" rect_w="4" rect_x="959" rect_y="0" width="4" >
  </QuadChar>
  <QuadChar id="338" offset_x="0" offset_y="0" rect_h="11" rect_w="6" rect_x="964" rect_y="0" width="6" >
  </QuadChar>
  <QuadChar id="339" offset_x="0" offset_y="0" rect_h="11" rect_w="6" rect_x="971" rect_y="0" width="6" >
  </QuadChar>
  <QuadChar id="346" offset_x="0" offset_y="0" rect_h="11" rect_w="6" rect_x="978" rect_y="0" width="6" >
  </QuadChar>
  <QuadChar id="347" offset_x="0" offset_y="0" rect_h="11" rect_w="4" rect_x="985" rect_y="0" width="4" >
  </QuadChar>
  <QuadChar id="377" offset_x="0" offset_y="0" rect_h="11" rect_w="6" rect_x="990" rect_y="0" width="6" >
  </QuadChar>
  <QuadChar id="378" offset_x="0" offset_y="0" rect_h="11" rect_w="4" rect_x="997" rect_y="0" width="4" >
  </QuadChar>
  <QuadChar id="379" offset_x="0" offset_y="0" rect_h="11" rect_w="6" rect_x="1002" rect_y="0" width="6" >
  </QuadChar>
  <QuadChar id="380" offset_x="0" offset_y="0" rect_h="11" rect_w="4" rect_x="1009" rect_y="0" width="4" >
  </QuadChar>
  <QuadChar id="1025" offset_x="0" offset_y="0" rect_h="11" rect_w="6" rect_x="1014" rect_y="0" width="6" >
  </QuadChar>
  <QuadChar id="1040" offset_x="0" offset_y="0" rect_h="11" rect_w="6" rect_x="1021" rect_y="0" width="6" >
  </QuadChar>
  <QuadChar id="1041" offset_x="0" offset_y="0" rect_h="11" rect_w="6" rect_x="1028" rect_y="0" width="6" >
  </QuadChar>
  <QuadChar id="1042" offset_x="0" offset_y="0" rect_h="11" rect_w="6" rect_x="1035" rect_y="0" width="6" >
  </QuadChar>
  <QuadChar id="1043" offset_x="0" offset_y="0" rect_h="11" rect_w="6" rect_x="1042" rect_y="0" width="6" >
  </QuadChar>
  <QuadChar id="1044" offset_x="0" offset_y="0" rect_h="11" rect_w="6" rect_x="1049" rect_y="0" width="6" >
  </QuadChar>
  <QuadChar id="1045" offset_x="0" offset_y="0" rect_h="11" rect_w="6" rect_x="1056" rect_y="0" width="6" >
  </QuadChar>
  <QuadChar id="1046" offset_x="0" offset_y="0" rect_h="11" rect_w="6" rect_x="1063" rect_y="0" width="6" >
  </QuadChar>
  <QuadChar id="1047" offset_x="0" offset_y="0" rect_h="11" rect_w="6" rect_x="1070" rect_y="0" width="6" >
  </QuadChar>
  <QuadChar id="1048" offset_x="0" offset_y="0" rect_h="11" rect_w="6" rect_x="1077" rect_y="0" width="6" >
  </QuadChar>
  <QuadChar id="1049" offset_x="0" offset_y="0" rect_h="11" rect_w="6" rect_x="1084" rect_y="0" width="6" >
  </QuadChar>
  <QuadChar id="1050" offset_x="0" offset_y="0" rect_h="11" rect_w="6" rect_x="1091" rect_y="0" width="6" >
  </QuadChar>
  <QuadChar id="1051" offset_x="0" offset_y="0" rect_h="11" rect_w="6" rect_x="1098" rect_y="0" width="6" >
  </QuadChar>
  <QuadChar id="1052" offset_x="0" offset_y="0" rect_h="11" rect_w="6" rect_x="1105" rect_y="0" width="6" >
  </QuadChar>
  <QuadChar id="1053" offset_x="0" offset_y="0" rect_h="11" rect_w="6" rect_x="1112" rect_y="0" width="6" >
  </QuadChar>
  <QuadChar id="1054" offset_x="0" offset_y="0" rect_h="11" rect_w="6" rect_x="1119" rect_y="0" width="6" >
  </QuadChar>
  <QuadChar id="1055" offset_x="0" offset_y="0" rect_h="11" rect_w="6" rect_x="1126" rect_y="0" width="6" >
  </QuadChar>
  <QuadChar id="1056" offset_x="0" offset_y="0" rect_h="11" rect_w="6" rect_x="1133" rect_y="0" width="6" >
  </QuadChar>
  <QuadChar id="1057" offset_x="0" offset_y="0" rect_h="11" rect_w="6" rect_x="1140" rect_y="0" width="6" >
  </QuadChar>
  <QuadChar id="1058" offset_x="0" offset_y="0" rect_h="11" rect_w="6" rect_x="1147" rect_y="0" width="6" >
  </QuadChar>
  <QuadChar id="1059" offset_x="0" offset_y="0" rect_h="11" rect_w="6" rect_x="1154" rect_y="0" width="6" >
  </QuadChar>
  <QuadChar id="1060" offset_x="0" offset_y="0" rect_h="11" rect_w="6" rect_x="1161" rect_y="0" width="6" >
  </QuadChar>
  <QuadChar id="1061" offset_x="0" offset_y="0" rect_h="11" rect_w="6" rect_x="1168" rect_y="0" width="6" >
  </QuadChar>
  <QuadChar id="1062" offset_x="0" offset_y="0" rect_h="11" rect_w="6" rect_x="1175" rect_y="0" width="6" >
  </QuadChar>
  <QuadChar id="1063" offset_x="0" offset_y="0" rect_h="11" rect_w="6" rect_x="1182" rect_y="0" width="6" >
  </QuadChar>
  <QuadChar id="1064" offset_x="0" offset_y="0" rect_h="11" rect_w="6" rect_x="1189" rect_y="0" width="6" >
  </QuadChar>
  <QuadChar id="1065" offset_x="0" offset_y="0" rect_h="11" rect_w="6" rect_x="1196" rect_y="0" width="6" >
  </QuadChar>
  <QuadChar id="1066" offset_x="0" offset_y="0" rect_h="11" rect_w="6" rect_x="1203" rect_y="0" width="6" >
  </QuadChar>
  <QuadChar id="1067" offset_x="0" offset_y="0" rect_h="11" rect_w="6" rect_x="1210" rect_y="0" width="6" >
  </QuadChar>
  <QuadChar id="1068" offset_x="0" offset_y="0" rect_h="11" rect_w="5" rect_x="1217" rect_y="0" width="5" >
  </QuadChar>
  <QuadChar id="1069" offset_x="0" offset_y="0" rect_h="11" rect_w="6" rect_x="1223" rect_y="0" width="6" >
  </QuadChar>
  <QuadChar id="1070" offset_x="0" offset_y="0" rect_h="11" rect_w="6" rect_x="1230" rect_y="0" width="6" >
  </QuadChar>
  <QuadChar id="1071" offset_x="0" offset_y="0" rect_h="11" rect_w="6" rect_x="1237" rect_y="0" width="6" >
  </QuadChar>
  <QuadChar id="1072" offset_x="0" offset_y="0" rect_h="11" rect_w="4" rect_x="1244" rect_y="0" width="4" >
  </QuadChar>
  <QuadChar id="1073" offset_x="0" offset_y="0" rect_h="11" rect_w="4" rect_x="1249" rect_y="0" width="4" >
  </QuadChar>
  <QuadChar id="1074" offset_x="0" offset_y="0" rect_h="11" rect_w="4" rect_x="1254" rect_y="0" width="4" >
  </QuadChar>
  <QuadChar id="1075" offset_x="0" offset_y="0" rect_h="11" rect_w="4" rect_x="1259" rect_y="0" width="4" >
  </QuadChar>
  <QuadChar id="1076" offset_x="0" offset_y="0" rect_h="11" rect_w="5" rect_x="1264" rect_y="0" width="5" >
  </QuadChar>
  <QuadChar id="1077" offset_x="0" offset_y="0" rect_h="11" rect_w="4" rect_x="1270" rect_y="0" width="4" >
  </QuadChar>
  <QuadChar id="1078" offset_x="0" offset_y="0" rect_h="11" rect_w="6" rect_x="1275" rect_y="0" width="6" >
  </QuadChar>
  <QuadChar id="1079" offset_x="0" offset_y="0" rect_h="11" rect_w="4" rect_x="1282" rect_y="0" width="4" >
  </QuadChar>
  <QuadChar id="1080" offset_x="0" offset_y="0" rect_h="11" rect_w="6" rect_x="1287" rect_y="0" width="6" >
  </QuadChar>
  <QuadChar id="1081" offset_x="0" offset_y="0" rect_h="11" rect_w="6" rect_x="1294" rect_y="0" width="6" >
  </QuadChar>
  <QuadChar id="1082" offset_x="0" offset_y="0" rect_h="11" rect_w="4" rect_x="1301" rect_y="0" width="4" >
  </QuadChar>
  <QuadChar id="1083" offset_x="0" offset_y="0" rect_h="11" rect_w="5" rect_x="1306" rect_y="0" width="5" >
  </QuadChar>
  <QuadChar id="1084" offset_x="0" offset_y="0" rect_h="11" rect_w="6" rect_x="1312" rect_y="0" width="6" >
  </QuadChar>
  <QuadChar id="1085" offset_x="0" offset_y="0" rect_h="11" rect_w="4" rect_x="1319" rect_y="0" width="4" >
  </QuadChar>
  <QuadChar id="1086" offset_x="0" offset_y="0" rect_h="11" rect_w="4" rect_x="1324" rect_y="0" width="4" >
  </QuadChar>
  <QuadChar id="1087" offset_x="0" offset_y="0" rect_h="11" rect_w="4" rect_x="1329" rect_y="0" width="4" >
  </QuadChar>
  <QuadChar id="1088" offset_x="0" offset_y="0" rect_h="11" rect_w="4" rect_x="1334" rect_y="0" width="4" >
  </QuadChar>
  <QuadChar id="1089" offset_x="0" offset_y="0" rect_h="11" rect_w="4" rect_x="1339" rect_y="0" width="4" >
  </QuadChar>
  <QuadChar id="1090" offset_x="0" offset_y="0" rect_h="11" rect_w="4" rect_x="1344" rect_y="0" width="4" >
  </QuadChar>
  <QuadChar id="1091" offset_x="0" offset_y="0" rect_h="11" rect_w="4" rect_x="1349" rect_y="0" width="4" >
  </QuadChar>
  <QuadChar id="1092" offset_x="0" offset_y="0" rect_h="11" rect_w="6" rect_x="1354" rect_y="0" width="6" >
  </QuadChar>
  <QuadChar id="1093" offset_x="0" offset_y="0" rect_h="11" rect_w="4" rect_x="1361" rect_y="0" width="4" >
  </QuadChar>
  <QuadChar id="1094" offset_x="0" offset_y="0" rect_h="11" rect_w="4" rect_x="1366" rect_y="0" width="4" >
  </QuadChar>
  <QuadChar id="1095" offset_x="0" offset_y="0" rect_h="11" rect_w="4" rect_x="1371" rect_y="0" width="4" >
  </QuadChar>
  <QuadChar id="1096" offset_x="0" offset_y="0" rect_h="11" rect_w="6" rect_x="1376" rect_y="0" width="6" >
  </QuadChar>
  <QuadChar id="1097" offset_x="0" offset_y="0" rect_h="11" rect_w="6" rect_x="1383" rect_y="0" width="6" >
  </QuadChar>
  <QuadChar id="1098" offset_x="0" offset_y="0" rect_h="11" rect_w="5" rect_x="1390" rect_y="0" width="5" >
  </QuadChar>
  <QuadChar id="1099" offset_x="0" offset_y="0" rect_h="11" rect_w="6" rect_x="1396" rect_y="0" width="6" >
  </QuadChar>
  <QuadChar id="1100" offset_x="0" offset_y="0" rect_h="11" rect_w="4" rect_x="1403" rect_y="0" width="4" >
  </QuadChar>
  <QuadChar id="1101" offset_x="0" offset_y="0" rect_h="11" rect_w="4" rect_x="1408" rect_y="0" width="4" >
  </QuadChar>
  <QuadChar id="1102" offset_x="0" offset_y="0" rect_h="11" rect_w="6" rect_x="1413" rect_y="0" width="6" >
  </QuadChar>
  <QuadChar id="1103" offset_x="0" offset_y="0" rect_h="11" rect_w="6" rect_x="1420" rect_y="0" width="6" >
  </QuadChar>
  <QuadChar id="1105" offset_x="0" offset_y="0" rect_h="11" rect_w="4" rect_x="1427" rect_y="0" width="4" >
  </QuadChar>
  <QuadChar id="8211" offset_x="0" offset_y="0" rect_h="11" rect_w="6" rect_x="1432" rect_y="0" width="6" >
  </QuadChar>
  <QuadChar id="8212" offset_x="0" offset_y="0" rect_h="11" rect_w="6" rect_x="1439" rect_y="0" width="6" >
  </QuadChar>
  <QuadChar id="8217" offset_x="0" offset_y="0" rect_h="11" rect_w="2" rect_x="1446" rect_y="0" width="2" >
  </QuadChar>
  <QuadChar id="8220" offset_x="0" offset_y="0" rect_h="11" rect_w="4" rect_x="1449" rect_y="0" width="4" >
  </QuadChar>
  <QuadChar id="8221" offset_x="0" offset_y="0" rect_h="11" rect_w="4" rect_x="1454" rect_y="0" width="4" >
  </QuadChar>
  <QuadChar id="8222" offset_x="0" offset_y="0" rect_h="11" rect_w="4" rect_x="1459" rect_y="0" width="4" >
  </QuadChar>
  <QuadChar id="8230" offset_x="0" offset_y="0" rect_h="11" rect_w="6" rect_x="1464" rect_y="0" width="6" >
  </QuadChar>
  <QuadChar id="8734" offset_x="0" offset_y="0" rect_h="11" rect_w="10" rect_x="1471" rect_y="0" width="10" >
  </QuadChar>
</FontData>
